pydobby/__init__.py
pydobby/request.py
pydobby/response.py
pydobby/router.py
pydobby/server.py
pydobby-0.1.2.dist-info/LICENSE
pydobby-0.1.2.dist-info/METADATA
pydobby-0.1.2.dist-info/WHEEL
pydobby-0.1.2.dist-info/RECORD
