Metadata-Version: 2.1
Name: pydobby
Version: 0.1.2
Summary: Lightweight HTTP server framework
License: MIT
Author: zaki
Author-email: ahmed.zaki1998@outlook.com
Requires-Python: >=3.10,<4.0
Classifier: License :: OSI Approved :: MIT License
Classifier: Programming Language :: Python :: 3
Classifier: Programming Language :: Python :: 3.10
Classifier: Programming Language :: Python :: 3.11
Classifier: Programming Language :: Python :: 3.12
Classifier: Programming Language :: Python :: 3.13
